formula1archive/__init__.py
formula1archive/dataextractor.py
formula1archive/dataviz.py
formula1archive-0.2.1.dist-info/METADATA
formula1archive-0.2.1.dist-info/WHEEL
formula1archive-0.2.1.dist-info/top_level.txt
formula1archive-0.2.1.dist-info/RECORD
