Metadata-Version: 2.1
Name: formula1archive
Version: 0.2.1
Summary: Web scraping library to extract race results from F1 website
Home-page: UNKNOWN
Author: Me
License: MIT
Platform: UNKNOWN
Requires-Dist: pandas
Requires-Dist: bs4
Requires-Dist: plotly
Requires-Dist: matplotlib
